{
  "Top": "convolve",
  "RtlTop": "convolve",
  "RtlPrefix": "",
  "RtlSubPrefix": "convolve_",
  "SourceLanguage": "cpp",
  "HostMachineBits": "64",
  "FunctionProtocol": "ap_ctrl_hs",
  "ResetStyle": "control",
  "Target": {
    "Family": "virtexuplus",
    "Device": "xcvu11p",
    "Package": "-flga2577",
    "Speed": "-1-e",
    "Triple": "fpga64-xilinx-none"
  },
  "Args": {
    "x": {
      "index": "0",
      "direction": "in",
      "srcType": "int*",
      "srcSize": "32",
      "hwRefs": [
        {
          "type": "port",
          "interface": "x_address0",
          "name": "x_address0",
          "usage": "address",
          "direction": "out"
        },
        {
          "type": "port",
          "interface": "x_ce0",
          "name": "x_ce0",
          "usage": "control",
          "direction": "out"
        },
        {
          "type": "port",
          "interface": "x_q0",
          "name": "x_q0",
          "usage": "data",
          "direction": "in"
        },
        {
          "type": "port",
          "interface": "x_address1",
          "name": "x_address1",
          "usage": "address",
          "direction": "out"
        },
        {
          "type": "port",
          "interface": "x_ce1",
          "name": "x_ce1",
          "usage": "control",
          "direction": "out"
        },
        {
          "type": "port",
          "interface": "x_q1",
          "name": "x_q1",
          "usage": "data",
          "direction": "in"
        }
      ]
    },
    "kernel": {
      "index": "1",
      "direction": "in",
      "srcType": "int*",
      "srcSize": "32",
      "hwRefs": [
        {
          "type": "port",
          "interface": "kernel_address0",
          "name": "kernel_address0",
          "usage": "address",
          "direction": "out"
        },
        {
          "type": "port",
          "interface": "kernel_ce0",
          "name": "kernel_ce0",
          "usage": "control",
          "direction": "out"
        },
        {
          "type": "port",
          "interface": "kernel_q0",
          "name": "kernel_q0",
          "usage": "data",
          "direction": "in"
        },
        {
          "type": "port",
          "interface": "kernel_address1",
          "name": "kernel_address1",
          "usage": "address",
          "direction": "out"
        },
        {
          "type": "port",
          "interface": "kernel_ce1",
          "name": "kernel_ce1",
          "usage": "control",
          "direction": "out"
        },
        {
          "type": "port",
          "interface": "kernel_q1",
          "name": "kernel_q1",
          "usage": "data",
          "direction": "in"
        }
      ]
    },
    "output": {
      "index": "2",
      "direction": "out",
      "srcType": "int*",
      "srcSize": "32",
      "hwRefs": [
        {
          "type": "port",
          "interface": "output_r_address0",
          "name": "output_r_address0",
          "usage": "address",
          "direction": "out"
        },
        {
          "type": "port",
          "interface": "output_r_ce0",
          "name": "output_r_ce0",
          "usage": "control",
          "direction": "out"
        },
        {
          "type": "port",
          "interface": "output_r_we0",
          "name": "output_r_we0",
          "usage": "control",
          "direction": "out"
        },
        {
          "type": "port",
          "interface": "output_r_d0",
          "name": "output_r_d0",
          "usage": "data",
          "direction": "out"
        }
      ]
    }
  },
  "HlsSolution": {
    "FlowTarget": "vivado",
    "ConfigTcl": [
      "config_cosim -rtl=vhdl",
      "config_cosim -tool=xsim"
    ],
    "DirectiveTcl": [
      "set_directive_top convolve -name convolve",
      "set_directive_top convolve -name convolve"
    ],
    "ProfileOption": "0",
    "ProfileType": "none",
    "KernelName": "convolve"
  },
  "ClockInfo": {
    "ClockName": "ap_clk",
    "ClockPeriod": "10",
    "Uncertainty": "2.7",
    "IsCombinational": "0",
    "II": "66",
    "Latency": "65"
  },
  "Xdc": {"OocClocks": ["create_clock -name ap_clk -period 10.000 [get_ports ap_clk]"]},
  "Ipx": {
    "Vendor": "xilinx.com",
    "Library": "hls",
    "Name": "convolve",
    "Version": "1.0",
    "DisplayName": "Convolve",
    "Revision": "2113811017",
    "Description": "An IP generated by Vitis HLS",
    "Taxonomy": "\/VITIS_HLS_IP",
    "AutoFamilySupport": "",
    "ZipFile": "xilinx_com_hls_convolve_1_0.zip"
  },
  "Files": {
    "CSource": ["..\/..\/convolution.cpp"],
    "Vhdl": [
      "impl\/vhdl\/convolve_convolve_Pipeline_VITIS_LOOP_21_2.vhd",
      "impl\/vhdl\/convolve_flow_control_loop_pipe_sequential_init.vhd",
      "impl\/vhdl\/convolve_mul_32s_32s_32_1_1.vhd",
      "impl\/vhdl\/convolve.vhd"
    ],
    "Verilog": [
      "impl\/verilog\/convolve_convolve_Pipeline_VITIS_LOOP_21_2.v",
      "impl\/verilog\/convolve_flow_control_loop_pipe_sequential_init.v",
      "impl\/verilog\/convolve_mul_32s_32s_32_1_1.v",
      "impl\/verilog\/convolve.v"
    ],
    "IpMisc": ["impl\/misc\/logo.png"],
    "CsynthXml": "syn\/report\/csynth.xml",
    "DebugDir": ".debug",
    "KernelXml": ".autopilot\/db\/kernel.internal.xml",
    "Xo": "",
    "XoHlsDir": "",
    "ProtoInst": [".debug\/convolve.protoinst"]
  },
  "SubcoreInfo": {
    "HasXpmMemory": false,
    "HasClockedDsp": false,
    "Ip": []
  },
  "Interfaces": {
    "ap_clk": {
      "type": "clock",
      "busTypeName": "clock",
      "mode": "slave",
      "busParams": {"ASSOCIATED_RESET": "ap_rst"},
      "portMap": {"ap_clk": "CLK"},
      "ports": ["ap_clk"]
    },
    "ap_rst": {
      "type": "reset",
      "busTypeName": "reset",
      "mode": "slave",
      "busParams": {"POLARITY": "ACTIVE_HIGH"},
      "portMap": {"ap_rst": "RST"},
      "ports": ["ap_rst"]
    },
    "ap_ctrl": {
      "type": "ap_ctrl",
      "busTypeName": "acc_handshake",
      "mode": "slave",
      "portMap": {
        "ap_start": "start",
        "ap_done": "done",
        "ap_idle": "idle",
        "ap_ready": "ready"
      },
      "ports": [
        "ap_done",
        "ap_idle",
        "ap_ready",
        "ap_start"
      ]
    },
    "x_address0": {
      "type": "data",
      "busTypeName": "data",
      "protocol": "ap_memory",
      "mode": "master",
      "dataWidth": "5",
      "portMap": {"x_address0": "DATA"},
      "ports": ["x_address0"],
      "constraints": [{
          "constraint_type": "pragma interface",
          "mode": "ap_memory",
          "register_option": "0",
          "argName": "x"
        }]
    },
    "x_q0": {
      "type": "data",
      "busTypeName": "data",
      "protocol": "ap_memory",
      "mode": "slave",
      "dataWidth": "32",
      "portMap": {"x_q0": "DATA"},
      "ports": ["x_q0"],
      "constraints": [{
          "constraint_type": "pragma interface",
          "mode": "ap_memory",
          "register_option": "0",
          "argName": "x"
        }]
    },
    "x_address1": {
      "type": "data",
      "busTypeName": "data",
      "protocol": "ap_memory",
      "mode": "master",
      "dataWidth": "5",
      "portMap": {"x_address1": "DATA"},
      "ports": ["x_address1"],
      "constraints": [{
          "constraint_type": "pragma interface",
          "mode": "ap_memory",
          "register_option": "0",
          "argName": "x"
        }]
    },
    "x_q1": {
      "type": "data",
      "busTypeName": "data",
      "protocol": "ap_memory",
      "mode": "slave",
      "dataWidth": "32",
      "portMap": {"x_q1": "DATA"},
      "ports": ["x_q1"],
      "constraints": [{
          "constraint_type": "pragma interface",
          "mode": "ap_memory",
          "register_option": "0",
          "argName": "x"
        }]
    },
    "kernel_address0": {
      "type": "data",
      "busTypeName": "data",
      "protocol": "ap_memory",
      "mode": "master",
      "dataWidth": "4",
      "portMap": {"kernel_address0": "DATA"},
      "ports": ["kernel_address0"],
      "constraints": [{
          "constraint_type": "pragma interface",
          "mode": "ap_memory",
          "register_option": "0",
          "argName": "kernel"
        }]
    },
    "kernel_q0": {
      "type": "data",
      "busTypeName": "data",
      "protocol": "ap_memory",
      "mode": "slave",
      "dataWidth": "32",
      "portMap": {"kernel_q0": "DATA"},
      "ports": ["kernel_q0"],
      "constraints": [{
          "constraint_type": "pragma interface",
          "mode": "ap_memory",
          "register_option": "0",
          "argName": "kernel"
        }]
    },
    "kernel_address1": {
      "type": "data",
      "busTypeName": "data",
      "protocol": "ap_memory",
      "mode": "master",
      "dataWidth": "4",
      "portMap": {"kernel_address1": "DATA"},
      "ports": ["kernel_address1"],
      "constraints": [{
          "constraint_type": "pragma interface",
          "mode": "ap_memory",
          "register_option": "0",
          "argName": "kernel"
        }]
    },
    "kernel_q1": {
      "type": "data",
      "busTypeName": "data",
      "protocol": "ap_memory",
      "mode": "slave",
      "dataWidth": "32",
      "portMap": {"kernel_q1": "DATA"},
      "ports": ["kernel_q1"],
      "constraints": [{
          "constraint_type": "pragma interface",
          "mode": "ap_memory",
          "register_option": "0",
          "argName": "kernel"
        }]
    },
    "output_r_address0": {
      "type": "data",
      "busTypeName": "data",
      "protocol": "ap_memory",
      "mode": "master",
      "dataWidth": "5",
      "portMap": {"output_r_address0": "DATA"},
      "ports": ["output_r_address0"],
      "constraints": [{
          "constraint_type": "pragma interface",
          "mode": "ap_memory",
          "register_option": "0",
          "argName": "output"
        }]
    },
    "output_r_d0": {
      "type": "data",
      "busTypeName": "data",
      "protocol": "ap_memory",
      "mode": "master",
      "dataWidth": "32",
      "portMap": {"output_r_d0": "DATA"},
      "ports": ["output_r_d0"],
      "constraints": [{
          "constraint_type": "pragma interface",
          "mode": "ap_memory",
          "register_option": "0",
          "argName": "output"
        }]
    }
  },
  "RtlPorts": {
    "ap_clk": {
      "dir": "in",
      "width": "1"
    },
    "ap_rst": {
      "dir": "in",
      "width": "1"
    },
    "ap_start": {
      "dir": "in",
      "width": "1"
    },
    "ap_done": {
      "dir": "out",
      "width": "1"
    },
    "ap_idle": {
      "dir": "out",
      "width": "1"
    },
    "ap_ready": {
      "dir": "out",
      "width": "1"
    },
    "x_address0": {
      "dir": "out",
      "width": "5"
    },
    "x_ce0": {
      "dir": "out",
      "width": "1"
    },
    "x_q0": {
      "dir": "in",
      "width": "32"
    },
    "x_address1": {
      "dir": "out",
      "width": "5"
    },
    "x_ce1": {
      "dir": "out",
      "width": "1"
    },
    "x_q1": {
      "dir": "in",
      "width": "32"
    },
    "kernel_address0": {
      "dir": "out",
      "width": "4"
    },
    "kernel_ce0": {
      "dir": "out",
      "width": "1"
    },
    "kernel_q0": {
      "dir": "in",
      "width": "32"
    },
    "kernel_address1": {
      "dir": "out",
      "width": "4"
    },
    "kernel_ce1": {
      "dir": "out",
      "width": "1"
    },
    "kernel_q1": {
      "dir": "in",
      "width": "32"
    },
    "output_r_address0": {
      "dir": "out",
      "width": "5"
    },
    "output_r_ce0": {
      "dir": "out",
      "width": "1"
    },
    "output_r_we0": {
      "dir": "out",
      "width": "1"
    },
    "output_r_d0": {
      "dir": "out",
      "width": "32"
    }
  },
  "ModuleInfo": {
    "Hierarchy": {
      "ModuleName": "convolve",
      "Instances": [{
          "ModuleName": "convolve_Pipeline_VITIS_LOOP_21_2",
          "InstanceName": "grp_convolve_Pipeline_VITIS_LOOP_21_2_fu_154"
        }]
    },
    "Info": {
      "convolve_Pipeline_VITIS_LOOP_21_2": {
        "FunctionProtocol": "ap_ctrl_hs",
        "isTaskLevelControl": "0",
        "isPipelined": "1",
        "isCombinational": "0",
        "isOneStateSeq": "0"
      },
      "convolve": {
        "FunctionProtocol": "ap_ctrl_hs",
        "isTaskLevelControl": "0",
        "isPipelined": "0",
        "isCombinational": "0",
        "isOneStateSeq": "0"
      }
    },
    "Metrics": {
      "convolve_Pipeline_VITIS_LOOP_21_2": {
        "Latency": {
          "LatencyBest": "17",
          "LatencyAvg": "17",
          "LatencyWorst": "17",
          "PipelineII": "17",
          "PipelineDepth": "",
          "PipelineType": "no"
        },
        "Timing": {
          "Target": "10.00",
          "Uncertainty": "2.70",
          "Estimate": "7.174"
        },
        "Loops": [{
            "Name": "VITIS_LOOP_21_2",
            "TripCount": "3",
            "Latency": "15",
            "PipelineII": "5",
            "PipelineDepth": "6"
          }],
        "Area": {
          "DSP": "6",
          "AVAIL_DSP": "9216",
          "UTIL_DSP": "~0",
          "FF": "213",
          "AVAIL_FF": "2592000",
          "UTIL_FF": "~0",
          "LUT": "685",
          "AVAIL_LUT": "1296000",
          "UTIL_LUT": "~0",
          "BRAM_18K": "0",
          "AVAIL_BRAM": "4032",
          "UTIL_BRAM": "0",
          "URAM": "0",
          "AVAIL_URAM": "960",
          "UTIL_URAM": "0"
        }
      },
      "convolve": {
        "Latency": {
          "LatencyBest": "65",
          "LatencyAvg": "65",
          "LatencyWorst": "65",
          "PipelineII": "66",
          "PipelineDepth": "",
          "PipelineType": "no"
        },
        "Timing": {
          "Target": "10.00",
          "Uncertainty": "2.70",
          "Estimate": "7.174"
        },
        "Loops": [{
            "Name": "VITIS_LOOP_18_1",
            "TripCount": "3",
            "Latency": "59",
            "PipelineII": "",
            "PipelineDepth": "20"
          }],
        "Area": {
          "DSP": "6",
          "AVAIL_DSP": "9216",
          "UTIL_DSP": "~0",
          "FF": "524",
          "AVAIL_FF": "2592000",
          "UTIL_FF": "~0",
          "LUT": "829",
          "AVAIL_LUT": "1296000",
          "UTIL_LUT": "~0",
          "BRAM_18K": "0",
          "AVAIL_BRAM": "4032",
          "UTIL_BRAM": "0",
          "URAM": "0",
          "AVAIL_URAM": "960",
          "UTIL_URAM": "0"
        }
      }
    }
  },
  "GenerateBdFiles": "0",
  "GenData": {
    "DataVersion": "0.2",
    "Time": "2024-11-06 17:37:07 +0330",
    "ToolName": "vitis_hls",
    "ToolVersion": "2023.2"
  }
}
